apiverve_weatherseasons/__init__.py
apiverve_weatherseasons/apiClient.py
apiverve_weatherseasons/exceptions.py
apiverve_weatherseasons/setup.py
apiverve_weatherseasons/setup_dep.py
apiverve_weatherseasons/tests/__init__.py
apiverve_weatherseasons/tests/test_api.py
apiverve_weatherseasons-1.1.5.dist-info/LICENSE
apiverve_weatherseasons-1.1.5.dist-info/METADATA
apiverve_weatherseasons-1.1.5.dist-info/WHEEL
apiverve_weatherseasons-1.1.5.dist-info/top_level.txt
apiverve_weatherseasons-1.1.5.dist-info/RECORD
